LICENSE
setup.cfg
setup.py
tickler.py
tickler.egg-info/PKG-INFO
tickler.egg-info/SOURCES.txt
tickler.egg-info/dependency_links.txt
tickler.egg-info/entry_points.txt
tickler.egg-info/requires.txt
tickler.egg-info/top_level.txt